{"label": "Friends to Lovers Romance",
 "description": "",
"list": [
{"label" : "99 Percent Mine , by Sally Thorne","isbns" : [ "9780062682161",
"9780062439611"
]},{"label" : "Appealed, by Emma Chase","isbns" : [ "9781442383203"
]},{"label" : "Booked on a Feeling , by Jayci Lee","isbns" : [ "9781250621146"
]},{"label" : "Count Your Lucky Stars , by Alexandria Bellefleur","isbns" : [ "9780063000889"
]},{"label" : "Crazy Stupid Bromance, by Lyssa Kay Adams","isbns" : [ "9781984806130"
]},{"label" : "Duke, Actually , by Jenny Holiday ","isbns" : [ "9780062952103"
]},{"label" : "Evvie Drake Starts Over, by Linda Holmes","isbns" : [ "9781432865702",
"9780525619246",
"9781984845733"
]},{"label" : "Friends Without Benefits : an unrequited romance, by Penny Reid ","isbns" : [ "9780989281058"
]},{"label" : "Hard Sell, by Hudson Lin","isbns" : [ "9781335500151"
]},{"label" : "Hook, Line, and Sinker, by Tessa Bailey ","isbns" : [ "9780063045712",
"9780063045705",
"9780063045699"
]},{"label" : "Josh and Hazel's Guide to Not Dating, by Christina Lauren ","isbns" : [ "9781501165856",
"9781508259145"
]},{"label" : "Just Last Night, by Mhairi McFarlane ","isbns" : [ "9780063036871"
]},{"label" : "Like Lovers Do, by Tracey Livesay","isbns" : [ "9780062979568"
]},{"label" : "Love, Comment, Subscribe, by Cathy Yardley","isbns" : [ "9781542030007"
]},{"label" : "My Favorite Half-night Stand, by Christina Lauren ","isbns" : [ "9781501197406"
]},{"label" : "One Day in December , by Josie Silver ","isbns" : [ "9780525574682",
"9781984827135",
"9780525574705"
]},{"label" : "People We Meet on Vacation, by Emiy Henry ","isbns" : [ "9781984806758",
"9780593346808",
"9781432890193",
"9781984806765"
]},{"label" : "Queen Move, by Kennedy Ryan ","isbns" : [ "9781952457029"
]},{"label" : "Something to Talk About, by Meryl Wilsner ","isbns" : [ "9780593102527",
"9780593214473"
]},{"label" : "Take a Hint, Dani Brown , by Talia Hibbert","isbns" : [ "9780062941268"
]},{"label" : "The Cheat Sheet , by Sarah Adams ","isbns" : [ "9780593500767"
]},{"label" : "The Flatshare, by Beth O'Leary ","isbns" : [ "9781250295637",
"9781250223586"
]},{"label" : "The Friend Zone, by Kristen Callihan ","isbns" : [ "9780990715719",
"9781538715604"
]},{"label" : "The Game Plan, by Kristen Callihan ","isbns" : [ "9780990715788"
]},{"label" : "The Hot Shot, by Kristen Callihan ","isbns" : [ "9780990715740"
]},{"label" : "The Love Con, by Seressia Glass","isbns" : [ "9780593199053"
]},{"label" : "The One for You, by Roni Loren ","isbns" : [ "9781492693192",
"9781492693208"
]},{"label" : "The Paid Bridesmaid, by Sariah Wilson","isbns" : [ "9781638086598"
]},{"label" : "The Reunion , by Kayla Olson ","isbns" : [ "9781668001943"
]},{"label" : "The Switch, by Beth O'Leary ","isbns" : [ "9781250769862",
"9781250751850",
"9781250295675"
]},{"label" : "Things You Save in a Fire, by Katherine Center ","isbns" : [ "9781250047328",
"9781250221391",
"9781432868833",
"9781250221407"
]},{"label" : "Truth or Beard, by Penny Reid ","isbns" : [ "9781942874119"
]},{"label" : "Two Rogues Make a Right, by Cat Sebastian ","isbns" : [ "9780063050594",
"9780062821591",
"9780062820648"
]}]}












