{"label": "LGBTQ+ Representation in Sci-Fi and Fantasy",
 "description": "Authors, Stories, Characters, and Themes! This list has something for everyone looking for LGBTQ+ representation!",
"list": [
{"label" : "Light from Uncommon Stars, by Ryka Aoki","isbns" : [ "9781250824479"
]},{"label" : "Borderline, by Mishell Baker","isbns" : [ "9781508225287"
]},{"label" : "Karen Memory, by Elizabeth Bear","isbns" : [ "9780765375247"
]},{"label" : "Fireheart Tiger, by Aliette de Bodard","isbns" : [ "9781250793263"
]},{"label" : "Once & Future, by A. R. Capetta","isbns" : [ "9780316449250",
"9780316449274",
"9781549178856",
"9780316449267"
]},{"label" : "Sword in the Stars, by A. R. Capetta","isbns" : [ "9780316449298"
]},{"label" : "The Mask of Mirrors, by M. A. Carrick","isbns" : [ "9780316539678"
]},{"label" : "The Galaxy, and the Ground Within, by Becky Chambers","isbns" : [ "9780062936059",
"9780062936035",
"9780062936042"
]},{"label" : "The Long Way to a Small, Angry Planet, by Becky Chambers","isbns" : [ "9781515977278",
"9780062444134",
"9780062444127"
]},{"label" : "A Psalm for the Wild-Built, by Becky Chambers","isbns" : [ "9781250236210",
"9781250807748",
"9781250236227",
"9781250236227"
]},{"label" : "We Could be Heroes, by Mike Chen","isbns" : [ "9780778331391",
"9781488077111",
"9781488210587",
"9781488260582"
]},{"label" : "Black Water Sister, by Zen Cho","isbns" : [ "9780425283431",
"9780451487995",
"9781980036036"
]},{"label" : "A Master of Djinn, by P. Djèlí Clark","isbns" : [ "9781250807731",
"9781250267689"
]},{"label" : "The Prey of Gods, by Nicky Drayden","isbns" : [ "9780062493033",
"9780062850270"
]},{"label" : "The Disasters, by M. K. England","isbns" : [ "9780062657671",
"9780062937933"
]},{"label" : "Upright Women Wanted, by Sarah Gailey","isbns" : [ "9781250213587",
"9781541439443"
]},{"label" : "American Hippo, by Sarah Gailey","isbns" : [ "9781250176431"
]},{"label" : "This Is How You Lose the Time War, by Max Gladstone","isbns" : [ "9781534431010",
"9781508287056",
"9781534430990"
]},{"label" : "The Witch's Heart, by Genevieve Gornichec","isbns" : [ "9780593099940",
"9780593099957"
]},{"label" : "The Outside, by Ada Hoffmann","isbns" : [ "9780857668134",
"9780857668141"
]},{"label" : "The Fallen, by Ada Hoffmann","isbns" : [ "9780857668684"
]},{"label" : "The Light Brigade, by Kameron Hurley","isbns" : [ "9781481447966",
"9781508280408"
]},{"label" : "We Are the Ants, by Shaun David Hutchinson","isbns" : [ "9781481449632"
]},{"label" : "The All-Consuming World, by Cassandra Khaw","isbns" : [ "9781645660200"
]},{"label" : "Under the Whispering Door, by TJ Klune","isbns" : [ "9781250217349",
"9781250790163",
"9781250217332",
"9781250217332"
]},{"label" : "Magic's Pawn, by Mercedes Lackey","isbns" : [ "9780886773526",
"9781101121412"
]},{"label" : "Provenance, by Ann Leckie","isbns" : [ "9780316388672"
]},{"label" : "Not Your Sidekick, by C. B. Lee","isbns" : [ "9781945053047"
]},{"label" : "The Lady's Guide to Petticoats and Piracy, by Mackenzi Lee","isbns" : [ "9780062795328",
"9780062855954",
"9781982553401",
"9780062855947"
]},{"label" : "Persephone Station, by Stina Leicht","isbns" : [ "9781534414600"
]},{"label" : "Adaptation, by Malinda Lo","isbns" : [ "9798200660834",
"9780316197960",
"9780316214483"
]},{"label" : "Summer Sons, by Lee Mandelo","isbns" : [ "9781250826763"
]},{"label" : "A Marvellous Light, by Freya Marske","isbns" : [ "9781250788870",
"9781250788894",
"9781250824851",
"9781250788894"
]},{"label" : "A Desolation Called Peace, by Arkady Martine","isbns" : [ "9781250186461"
]},{"label" : "Winter's Orbit, by Everina Maxwell","isbns" : [ "9781250790194",
"9781250758859"
]},{"label" : "Across the Green Grass Fields, by Seanan McGuire","isbns" : [ "9781250790101",
"9781250213594",
"9781250213600",
"9781250790101"
]},{"label" : "We Set the Dark on Fire, by Tehlor Kay Mejia","isbns" : [ "9780062691330",
"9780062691316",
"9780062907943",
"9780062691323"
]},{"label" : "Gideon the Ninth, by Tamsyn Muir","isbns" : [ "9781250313195",
"9781980004899"
]},{"label" : "Girls of Paper and Fire, by Natasha Ngan","isbns" : [ "9780316561365",
"9781478992691"
]},{"label" : "A Study in Honor, by Claire O'Dell","isbns" : [ "9780062699305"
]},{"label" : "Peaces, by Helen Oyeyemi","isbns" : [ "9780593192337",
"9780593394571",
"9781643589992"
]},{"label" : "She Who Became the Sun, by Shelley Parker-Chan","isbns" : [ "9781250807809",
"9781250621801",
"9781250621795"
]},{"label" : "Bluebird, by Ciel Pierlot","isbns" : [ "9780857669674"
]},{"label" : "We are Satellites, by Sarah Pinsker","isbns" : [ "9781984802606"
]},{"label" : "The Last 8, by Laura Pohl","isbns" : [ "9781492669890",
"9781974954490"
]},{"label" : "Witchmark, by C. L. Polk","isbns" : [ "9781250162687"
]},{"label" : "Soulstar, by C. L. Polk","isbns" : [ "9781250203564"
]},{"label" : "The Kingdoms, by Natasha Pulley","isbns" : [ "9781635576085",
"9781635576092"
]},{"label" : "The Light of the Midnight Stars, by Rena Rossner","isbns" : [ "9780316483469",
"9780316483803"
]},{"label" : "The Priory of the Orange Tree, by Samantha Shannon","isbns" : [ "9781635570281",
"9781408883464"
]},{"label" : "More Happy than Not: A Novel, by Adam Silvera","isbns" : [ "9781616955601"
]},{"label" : "White Trash Warlock, by David R. Slayton","isbns" : [ "9781094067964"
]},{"label" : "An Unkindness of Ghosts, by Rivers Solomon","isbns" : [ "9781617755880",
"9781617755996",
"9781538475041"
]},{"label" : "The Deep, by Rivers Solomon","isbns" : [ "9781534439863",
"9781508280309"
]},{"label" : "The Bone Shard Daughter, by Andrea Stewart","isbns" : [ "9780316541428"
]},{"label" : "The Jasmine Throne, by Tasha Suri","isbns" : [ "9780316538510"
]},{"label" : "Cemetery Boys, by Aiden Thomas","isbns" : [ "9781250619129",
"9781250250513",
"9781250250469",
"9781250250513"
]},{"label" : "The Chosen and the Beautiful, by Nghi Vo","isbns" : [ "9781250784780",
"9781250784797",
"9781250784797",
"9781432891480"
]},{"label" : "Siren queen, by Nghi Vo","isbns" : [ "9781250788832",
"9781250788856",
"9781250788856"
]},{"label" : "The Ruthless Lady's Guide to Wizardry, by C. M. Waggoner","isbns" : [ "9781984805867",
"9781984805874"
]},{"label" : "Malice: A Novel, by Heather Walter","isbns" : [ "9781984818652",
"9781984818669",
"9781984818669"
]},{"label" : "Affinity, by Sarah Waters","isbns" : [ "9781573221566",
"9781573228732"
]}]}
