{
    "label": "Alternate Reality and Virtual Reality",
    "description": "Explore the amazing man-made, virtual worlds in these novels that feature AR and VR themes!",
    "list": [
{
"label":"88 Names, by Matt Ruff",
"isbns": [
"9780062854674"
]
},
{
"label":"Accelerando, by Charles Stross",
"isbns": [
"9780441012848"
]
},
{
"label":"Arena, by Holly Jennings",
"isbns": [
"9781101988763"
]
},
{
"label":"Armada: A Novel, by Ernest Cline",
"isbns": [
"9780804149143",
"9780804137256",
"9780804137263"
]
},
{
"label":"Daemon: A Novel, by Daniel Suarez",
"isbns": [
"9780525951117"
]
},
{
"label":"The Demi-Monde: Winter, by Rod Rees",
"isbns": [
"9780062070340",
"9780062070357"
]
},
{
"label":"Ender's Game, by Orson Scott Card",
"isbns": [
"9780812550702",
"9780765378484",
"9781593974756"
]
},
{
"label":"Erebos It's A Game: It Watches You, by Ursula Poznanski",
"isbns": [
"9781554514601"
]
},
{
"label":"The Evaporation of Sofi Snow, by Mary Weber",
"isbns": [
"9780785211259"
]
},
{
"label":"The Eye of Minds, by James Dashner",
"isbns": [
"9780385741392",
"9780375984631",
"9780804122498"
]
},
{
"label":"Feed, by M. T. Anderson",
"isbns": [
"9780763617264",
"9780739344392",
"9780763651558"
]
},
{
"label":"Insignia, by S. J. Kincaid",
"isbns": [
"9780062092991",
"9780062132772"
]
},
{
"label":"The Leveller, by Julia Durango",
"isbns": [
"9780062314024"
]
},
{
"label":"Otherland: City of Golden Shadow, by Tad Williams",
"isbns": [
"9780886777104"
]
},
{
"label":"Otherworld, by Jason Segel",
"isbns": [
"9781101939321"
]
},
{
"label":"The Peripheral, by William Gibson",
"isbns": [
"9780399158445",
"9780553545920"
]
},
{
"label":"Ready Player One, by Ernest Cline",
"isbns": [
"9780307887436",
"9780307887450",
"9780525624837",
"9780307913159"
]
},
{
"label":"Seveneves, by Neal Stephenson",
"isbns": [
"9780062190376",
"9780062190413",
"9781501220227"
]
},
{
"label":"Snow Crash, by Neal Stephenson",
"isbns": [
"9780553898194"
]
},
{
"label":"The Three-Body Problem, by Cixin Liu",
"isbns": [
"9780765377067",
"9781427260338",
"9781466853447"
]
},
{
"label":"The Unseen World, by Liz Moore",
"isbns": [
"9781504724326"
]
},
{
"label":"Virtual Light, by William Gibson",
"isbns": [
"9780553074994"
]
}
]
}