{"label": "Run Forrest Run!",			
 "description": "Historical fiction novels with Tree-titles",			
"list": [					
{"label" : "A Country Road, a Tree","isbns" : [ "9781101947180"
]},{"label" : "A Crooked Tree","isbns" : [ "9780063049840"
]},{"label" : "Beneath the Apple Leaves","isbns" : [ "9781617739439"
]},{"label" : "Don't Die Under the Apple Tree","isbns" : [ "9780758279743"
]},{"label" : "Hemlock","isbns" : [ "9781952558146"
]},{"label" : "Lady Clementine","isbns" : [ "9781492666905",
"9781432872779",
"9781492666912"
]},{"label" : "Leaving Lucy Pear","isbns" : [ "9781594632655",
"9780698149922"
]},{"label" : "Magnolia Creek","isbns" : [ "9780786246656"
]},{"label" : "Sonoma Rose : an Elm Creek quilts novel","isbns" : [ "9780525952640"
]},{"label" : "The Darling Dahlias and the Cucumber Tree","isbns" : [ "9781101183571"
]},{"label" : "The Endless Forest","isbns" : [ "9780553805260",
"9781415966174"
]},{"label" : "The Fever Tree","isbns" : [ "9780399158247",
"9781410459381"
]},{"label" : "The Forest of Vanishing Stars","isbns" : [ "9781982158934",
"9781638080442"
]},{"label" : "The Huntress of Thornbeck Forest","isbns" : [ "9780718034504"
]},{"label" : "The Island of Missing Trees","isbns" : [ "9781635578591",
"9781635578607"
]},{"label" : "The Overstory","isbns" : [ "9780393635539",
"9780393635522",
"9780393356687"
]},{"label" : "The Phantom Tree","isbns" : [ "9781525805998"
]},{"label" : "The Plum Tree","isbns" : [ "9780758278449"
]},{"label" : "The Shattered Tree","isbns" : [ "9780062386274",
"9780062472625"
]},{"label" : "The Sugar Camp Quilt : an Elm Creek Quilts novel","isbns" : [ "9780743260176",
"9780786274956",
"9781419339004"
]},{"label" : "The Walnut Tree","isbns" : [ "9780062236999",
"9780062238382"
]},{"label" : "The Witch of Willow Hall","isbns" : [ "9781525833014"
]},{"label" : "Under the Tulip Tree","isbns" : [ "9781496446077"
]}]}					
